az_ai_healthcheck/__init__.py
az_ai_healthcheck/azure_ai_vision.py
az_ai_healthcheck/azure_openai.py
az_ai_healthcheck/models.py
az_ai_healthcheck-0.1.7.dist-info/METADATA
az_ai_healthcheck-0.1.7.dist-info/WHEEL
az_ai_healthcheck-0.1.7.dist-info/licenses/LICENSE
az_ai_healthcheck-0.1.7.dist-info/RECORD
