Metadata-Version: 2.4
Name: az-ai-healthcheck
Version: 0.1.7
Summary: Lightweight health checks for Azure OpenAI and Azure AI Vision
License: MIT
License-File: LICENSE
Keywords: azure,openai,vision,healthcheck,monitoring
Author: Minseok Song
Author-email: minseok.song@mssong.com
Requires-Python: >=3.10
Classifier: License :: OSI Approved :: MIT License
Classifier: Programming Language :: Python :: 3
Classifier: Programming Language :: Python :: 3.10
Classifier: Programming Language :: Python :: 3.11
Classifier: Programming Language :: Python :: 3.12
Classifier: Programming Language :: Python :: 3.13
Classifier: Programming Language :: Python :: 3.14
Provides-Extra: vision
Requires-Dist: azure-ai-vision-imageanalysis (>=1.0.0b2,<2.0.0) ; extra == "vision"
Requires-Dist: requests (>=2.28,<3)
Project-URL: Repository, https://github.com/skytin1004/az-ai-healthcheck
